wxyz/lab/__init__.py
wxyz/lab/_version.py
wxyz/lab/base.py
wxyz/lab/install.json
wxyz/lab/widget_dock.py
wxyz/lab/widget_editor.py
wxyz/lab/widget_markdown.py
wxyz/lab/widget_term.py
wxyz/lab/js/LICENSE.txt
wxyz/lab/js/README.md
wxyz/lab/js/package.json
wxyz/lab/labextension/package.json
wxyz/lab/labextension/static/1050.465598e840dc6a9f4ea9.js
wxyz/lab/labextension/static/133.467495d7913473453935.js
wxyz/lab/labextension/static/1333.f45e88e74a20f02c476a.js
wxyz/lab/labextension/static/1400.44ecfd6d858496711c53.js
wxyz/lab/labextension/static/1477.adf9b439b717e58bf299.js
wxyz/lab/labextension/static/1568.e2f4354e5fa159411782.js
wxyz/lab/labextension/static/1630.ff30976f3d302315bc1b.js
wxyz/lab/labextension/static/1667.52ffe636f32689996083.js
wxyz/lab/labextension/static/2190.f235e2ef111989d46111.js
wxyz/lab/labextension/static/2190.f235e2ef111989d46111.js.LICENSE.txt
wxyz/lab/labextension/static/2555.3739ee67df66dbdd3231.js
wxyz/lab/labextension/static/2725.223cf7604ad07db942bc.js
wxyz/lab/labextension/static/2741.1196cc9fa1f38131fb90.js
wxyz/lab/labextension/static/2843.094a6152314c497df338.js
wxyz/lab/labextension/static/2914.daaa19d8dcd29676c6a5.js
wxyz/lab/labextension/static/3476.8d03fb37eec1d1e958fe.js
wxyz/lab/labextension/static/383.26fa8de2713099011527.js
wxyz/lab/labextension/static/3959.2912479dc427d2627e70.js
wxyz/lab/labextension/static/4024.e33b3008ee4f8da03490.js
wxyz/lab/labextension/static/4057.e02866340dcb36410b29.js
wxyz/lab/labextension/static/4109.1d44e9e782c8e43d1acc.js
wxyz/lab/labextension/static/4496.7c06ba3f5b39d917f21c.js
wxyz/lab/labextension/static/451.e038ef50a4fbc0b1ddf9.js
wxyz/lab/labextension/static/4534.026e4eb565ef049fcb29.js
wxyz/lab/labextension/static/4561.f4b950990ac87010aeda.js
wxyz/lab/labextension/static/4814.26e1d9fb325cc4042050.js
wxyz/lab/labextension/static/4865.61161ae40b30f10d4655.js
wxyz/lab/labextension/static/4898.7f812e547d03cfc49839.js
wxyz/lab/labextension/static/4929.874634bdf8011f386e7d.js
wxyz_lab-0.5.1.dist-info/LICENSE.txt
wxyz_lab-0.5.1.dist-info/METADATA
wxyz_lab-0.5.1.dist-info/WHEEL
wxyz_lab-0.5.1.dist-info/top_level.txt
wxyz_lab-0.5.1.dist-info/RECORD
